gnucash_reports/__init__.py
gnucash_reports/periods.py
gnucash_reports/utilities.py
gnucash_reports/wrapper.py
gnucash_reports/collate/__init__.py
gnucash_reports/collate/bucket.py
gnucash_reports/collate/bucket_generation.py
gnucash_reports/collate/key_generator.py
gnucash_reports/collate/store.py
gnucash_reports/commands/__init__.py
gnucash_reports/commands/reports.py
gnucash_reports/commands/update_prices.py
gnucash_reports/configuration/__init__.py
gnucash_reports/configuration/alphavantage.py
gnucash_reports/configuration/base.py
gnucash_reports/configuration/currency.py
gnucash_reports/configuration/current_date.py
gnucash_reports/configuration/expense_categories.py
gnucash_reports/configuration/inflation.py
gnucash_reports/configuration/investment_allocations.py
gnucash_reports/configuration/register_core.py
gnucash_reports/configuration/tax_tables.py
gnucash_reports/reports/__init__.py
gnucash_reports/reports/account_levels.py
gnucash_reports/reports/account_usage_categories.py
gnucash_reports/reports/base.py
gnucash_reports/reports/budget_level.py
gnucash_reports/reports/cash_flow.py
gnucash_reports/reports/credit_usage.py
gnucash_reports/reports/expenses_monthly.py
gnucash_reports/reports/income_expenses.py
gnucash_reports/reports/income_tax.py
gnucash_reports/reports/investment_balance.py
gnucash_reports/reports/net_worth.py
gnucash_reports/reports/retirement_401k.py
gnucash_reports/reports/savings_goals.py
gnucash_reports-0.2.0.dist-info/DESCRIPTION.rst
gnucash_reports-0.2.0.dist-info/METADATA
gnucash_reports-0.2.0.dist-info/RECORD
gnucash_reports-0.2.0.dist-info/WHEEL
gnucash_reports-0.2.0.dist-info/entry_points.txt
gnucash_reports-0.2.0.dist-info/metadata.json
gnucash_reports-0.2.0.dist-info/top_level.txt
